rpbtool/__init__.py
rpbtool/_version.py
rpbtool-0.0.1.dist-info/LICENSE
rpbtool-0.0.1.dist-info/METADATA
rpbtool-0.0.1.dist-info/WHEEL
rpbtool-0.0.1.dist-info/top_level.txt
rpbtool-0.0.1.dist-info/RECORD
